{
  "schema_version": "1.0",
  "dimension_labels": {
    "SUBJECT": "type",
    "CATEGORY": "genre",
    "SOURCE": "platform",
    "TIMEFRAME": "era",
    "GEOGRAPHICAL": "region"
  },
  "default_subject": "movie",
  "vocabulary": {
    "type": {
      "movie": ["movie", "film", "feature", "motion picture", "tv movie"],
      "series": ["series", "tv series", "show", "tv show"]
    },
    "genre": {
      "action": ["action", "action-packed"],
      "adventure": ["adventure"],
      "animation": ["animation", "animated"],
      "comedy": ["comedy", "funny", "parody"],
      "crime": ["crime", "detective", "heist", "gangster"],
      "documentary": ["documentary", "doc", "docuseries", "factual"],
      "family": ["family", "family-friendly"],
      "fantasy": ["fantasy", "magic", "mythology", "folklore"],
      "history": ["history", "historical", "period piece"],
      "horror": ["horror", "scary", "slasher", "creepy"],
      "music": ["music", "musical"],
      "mystery": ["mystery", "whodunit", "suspense"],
      "romance": ["romance", "love"],
      "sci_fi": ["sci-fi", "science fiction", "scifi" , "futuristic", "cyberpunk"],
      "sport": ["sport", "athletic"],
      "reality": ["reality-tv", "reality", "unscripted"],
      "thriller": ["thriller"],
      "western": ["western", "cowboy"],
      "war": ["war", "military"]
    },
    "platform": {
      "netflix": ["netflix", "nf"],
      "hbo_max": ["hbo max", "hbomax", "hbo"],
      "disney_plus": ["disney+", "disney plus", "disneyplus"],
      "amazon_prime": ["amazon prime", "prime video", "primevideo", "prime"],
      "hulu": ["hulu"],
      "apple_tv_plus": ["apple tv+", "apple tv plus", "appletv+"],
      "peacock": ["peacock"],
      "paramount+": ["paramount+", "paramount plus"],
      "youtube": ["youtube", "youtube movies", "yt"],
      "imdb_tv": ["imdb", "imdb tv"]
    },
    "region": {
      "us": ["hollywood"],
      "south_korea": ["k-drama", "k-dramas", "kdrama", "kdramas", "korean drama"],
      "india": ["bollywood"]
    }
  }
}
